LICENSE
MANIFEST.in
README.md
setup.cfg
setup.py
nxbt/__init__.py
nxbt/bluez.py
nxbt/cli.py
nxbt/logging.py
nxbt/nxbt.py
nxbt/tui.py
nxbt/controller/__init__.py
nxbt/controller/controller.py
nxbt/controller/input.py
nxbt/controller/protocol.py
nxbt/controller/server.py
nxbt/controller/utils.py
nxbt/controller/sdp/switch-controller.xml
nxbt/web/__init__.py
nxbt/web/app.py
nxbt/web/cert.py
nxbt/web/static/favicon.png
nxbt/web/static/joyconl.svg
nxbt/web/static/joyconr.svg
nxbt/web/static/procon-transparent.svg
nxbt/web/static/procon.svg
nxbt/web/static/css/main.css
nxbt/web/static/js/main.js
nxbt/web/static/js/socket.io.js
nxbt/web/templates/index.html
nxbt_naibaoofficial.egg-info/PKG-INFO
nxbt_naibaoofficial.egg-info/SOURCES.txt
nxbt_naibaoofficial.egg-info/dependency_links.txt
nxbt_naibaoofficial.egg-info/entry_points.txt
nxbt_naibaoofficial.egg-info/not-zip-safe
nxbt_naibaoofficial.egg-info/requires.txt
nxbt_naibaoofficial.egg-info/top_level.txt