Metadata-Version: 2.1
Name: nxbt-naibaoofficial
Version: 1.0.0
Summary: nxbt marco enhanced by naibaooffical
Home-page: https://pypi.python.org/pypi/nxbt
Author: Reece Walsh
Author-email: reece@brikwerk.com
License: MIT
Project-URL: Code, https://github.com/Brikwerk/nxbt
Project-URL: Issue tracker, https://github.com/Brikwerk/nxbt/issues
Platform: any
Classifier: Development Status :: 3 - Alpha
Classifier: Intended Audience :: Developers
Classifier: License :: OSI Approved :: MIT License
Classifier: Operating System :: OS Independent
Classifier: Programming Language :: Python
Classifier: Programming Language :: Python :: 3.6
Classifier: Programming Language :: Python :: 3.7
Classifier: Programming Language :: Python :: 3.8
Classifier: Topic :: Software Development :: Libraries :: Python Modules
Requires-Python: >=3.6
